pathcensus/__init__.py
pathcensus/definitions.py
pathcensus/graph.py
pathcensus/inference.py
pathcensus/pathcensus.py
pathcensus/types.py
pathcensus/utils.py
pathcensus/core/__init__.py
pathcensus/core/graph.py
pathcensus/core/parallel.py
pathcensus/core/random.py
pathcensus/core/types.py
pathcensus/nullmodels/__init__.py
pathcensus/nullmodels/base.py
pathcensus/nullmodels/ubcm.py
pathcensus/nullmodels/uecm.py
pathcensus-0.1.dist-info/AUTHORS.rst
pathcensus-0.1.dist-info/LICENSE
pathcensus-0.1.dist-info/METADATA
pathcensus-0.1.dist-info/WHEEL
pathcensus-0.1.dist-info/top_level.txt
pathcensus-0.1.dist-info/RECORD
