Metadata-Version: 2.1
Name: pathcensus
Version: 0.1
Summary: Structural similarity and complementarity coefficients for undirected networks based on efficient counting
Author-email: Szymon Talaga <stalaga@protonmail.com>
License: The MIT License (MIT)        
Project-URL: documentation, https://pathcensus.readthedocs.io/en/latest/
Project-URL: repository, https://github.com/sztal/pathcensus
Project-URL: changelog, https://github.com/sztal/pathcensus/blob/master/HISTORY.rst
Keywords: networks,graphs,undirected,weighted,bipartite,network science,network geometry,triples,quadruples,triangles,quadrangles,path census,motifs,relational principles,homophily,similarity,complementarity,structural equivalence,random geometric graph,latent space model,exponential random graph,ergm
Classifier: Programming Language :: Python :: 3
Classifier: Natural Language :: English
Classifier: License :: OSI Approved :: MIT License
Classifier: Operating System :: OS Independent
Requires-Python: >=3.8
License-File: LICENSE
License-File: AUTHORS.rst
Requires-Dist: numpy (>=1.20)
Requires-Dist: numba (>=0.50)
Requires-Dist: scipy (>=1.7)
Requires-Dist: pandas (>=1.3)
Requires-Dist: statsmodels (>=0.12)
Requires-Dist: NEMtropy (>=2.0)
Requires-Dist: tqdm (>=4.62)
Provides-Extra: docs
Requires-Dist: Sphinx (>=4.3) ; extra == 'docs'
Requires-Dist: sphinx-rtd-theme (>=1.0) ; extra == 'docs'
Requires-Dist: sphinxcontrib-bibtex (>=2.4) ; extra == 'docs'
Provides-Extra: test
Requires-Dist: ipython (>=7.26) ; extra == 'test'
Requires-Dist: pylint (>=2.9) ; extra == 'test'
Requires-Dist: pytest (>=6.2) ; extra == 'test'
Requires-Dist: pytest-runner (>=5.3) ; extra == 'test'
Requires-Dist: pytest-pylint (>=0.18) ; extra == 'test'
Requires-Dist: pytest-cov (>=3.0.0) ; extra == 'test'
Requires-Dist: python-igraph (>=0.9) ; extra == 'test'
Requires-Dist: networkx (>=2.6) ; extra == 'test'
